{"_id":{"$oid":"5cd692bfc7572e3fe47b4e9d"},"github_id":"","name":"james","type":1.0,"phone":"18450087586","img_url":"","email":"1581994988@qq.com","introduce":"加班到天明，学习到昏厥!!! ","avatar":"user","location":"user","password":"28637353beea307d2f9b94c037e8fd11","create_time":{"$date":"2019-05-11T09:15:43.845Z"},"update_time":{"$date":"2019-05-11T09:15:43.845Z"},"id":9.0,"__v":0.0}
{"_id":{"$oid":"5cf7da9081d7d1464c20f934"},"github_id":"","name":"admin","type":0.0,"phone":"18450087586","img_url":"","email":"1204788939@qq.com","introduce":"加班到天明，学习到昏厥!!!","avatar":"../assets/user.png","location":"user","password":"19a68bf40c22c05cfff615950f89cb5b","create_time":{"$date":"2019-06-05T15:06:56.261Z"},"update_time":{"$date":"2019-06-05T15:06:56.261Z"},"id":14.0,"__v":0.0}
